datasette_sqlite_url_lite/__init__.py
datasette_sqlite_url_lite-0.1.dist-info/LICENSE
datasette_sqlite_url_lite-0.1.dist-info/METADATA
datasette_sqlite_url_lite-0.1.dist-info/WHEEL
datasette_sqlite_url_lite-0.1.dist-info/entry_points.txt
datasette_sqlite_url_lite-0.1.dist-info/top_level.txt
datasette_sqlite_url_lite-0.1.dist-info/RECORD
