Metadata-Version: 2.1
Name: datasette-sqlite-url-lite
Version: 0.1
Summary: A pure Python alternative to sqlite-url ready to be used in Datasette Lite
Home-page: https://github.com/simonw/datasette-sqlite-url-lite
Author: Simon Willison
License: Apache License, Version 2.0
Project-URL: Issues, https://github.com/simonw/datasette-sqlite-url-lite/issues
Project-URL: CI, https://github.com/simonw/datasette-sqlite-url-lite/actions
Project-URL: Changelog, https://github.com/simonw/datasette-sqlite-url-lite/releases
Classifier: Framework :: Datasette
Classifier: License :: OSI Approved :: Apache Software License
Requires-Python: >=3.7
License-File: LICENSE
Requires-Dist: datasette
Provides-Extra: test
Requires-Dist: pytest ; extra == 'test'
Requires-Dist: pytest-asyncio ; extra == 'test'
